{
  "parent":"minecraft:item/handheld_rod",
  "textures":{
    "layer0":"minecraft:item/carrot_on_a_stick"
  },

  "overrides":[
    {"predicate":{"custom_model_data":1}, "model":"keiba_assistant:item/whip_1"},
    {"predicate":{"custom_model_data":2}, "model":"keiba_assistant:item/whip_2"},
    {"predicate":{"custom_model_data":3}, "model":"keiba_assistant:item/whip_3"},
    {"predicate":{"custom_model_data":4}, "model":"keiba_assistant:item/whip_4"},
    {"predicate":{"custom_model_data":5}, "model":"minecraft:item/carrot_on_a_stick"}
  ]
}